whaleman/__init__.py
whaleman/library.py
whaleman/logs.py
whaleman/main.py
whaleman-0.1.8.dist-info/entry_points.txt
whaleman-0.1.8.dist-info/WHEEL
whaleman-0.1.8.dist-info/METADATA
whaleman-0.1.8.dist-info/RECORD
