Metadata-Version: 2.1
Name: whaleman
Version: 0.1.8
Summary: docker image versioning
License: this aplication used versioning of docker image, using some configuration
Author: rede akbar wijaya
Author-email: rede@soberdev.com
Requires-Python: >=3.9,<4.0
Classifier: License :: Other/Proprietary License
Classifier: Programming Language :: Python :: 3
Classifier: Programming Language :: Python :: 3.9
Classifier: Programming Language :: Python :: 3.10
Requires-Dist: click (>=8.1.3,<9.0.0)
Requires-Dist: colorama (==0.4.5)
Requires-Dist: docker (>=6.0.0,<7.0.0)
